davidkhala/ai/model/__init__.py
davidkhala/ai/model/chat.py
davidkhala/ai/model/garden.py
davidkhala_ai_types-0.0.0.dist-info/METADATA
davidkhala_ai_types-0.0.0.dist-info/WHEEL
davidkhala_ai_types-0.0.0.dist-info/RECORD
