Metadata-Version: 2.4
Name: davidkhala.ai.types
Version: 0.0.0
Summary: types of ai modules
Requires-Python: >=3.10
